llm_fragments_tmux.py
llm_fragments_tmux-0.1.0a2.dist-info/licenses/LICENSE
llm_fragments_tmux-0.1.0a2.dist-info/METADATA
llm_fragments_tmux-0.1.0a2.dist-info/WHEEL
llm_fragments_tmux-0.1.0a2.dist-info/entry_points.txt
llm_fragments_tmux-0.1.0a2.dist-info/top_level.txt
llm_fragments_tmux-0.1.0a2.dist-info/RECORD
