Metadata-Version: 2.4
Name: llm-fragments-tmux
Version: 0.1.0a2
Summary: llm plugins for loading tmux panes
Author: kj-9
License-Expression: Apache-2.0
Project-URL: Homepage, https://github.com/kj-9/llm-fragments-tmux
Project-URL: Changelog, https://github.com/kj-9/llm-fragments-tmux/releases
Project-URL: Issues, https://github.com/kj-9/llm-fragments-tmux/issues
Project-URL: CI, https://github.com/kj-9/llm-fragments-tmux/actions
Requires-Python: >=3.10
License-File: LICENSE
Requires-Dist: llm
Provides-Extra: test
Requires-Dist: pytest; extra == "test"
Requires-Dist: pytest-xdist; extra == "test"
Dynamic: license-file
